ds_helper/__init__.py
ds_helper/dicts.py
ds_helper/lists.py
python_pool_ex09-0.0.1.dist-info/LICENCE
python_pool_ex09-0.0.1.dist-info/METADATA
python_pool_ex09-0.0.1.dist-info/WHEEL
python_pool_ex09-0.0.1.dist-info/top_level.txt
python_pool_ex09-0.0.1.dist-info/RECORD
