Metadata-Version: 2.1
Name: python-pool-ex09
Version: 0.0.1
Summary: Python for datascience bootcamp exercice number 9
Home-page: https://github.com/ytouate/1337-PYTHON-POOL
Author: ytouate
Classifier: Programming Language :: Python :: 3
Classifier: License :: OSI Approved :: MIT License
Classifier: Operating System :: OS Independent
License-File: LICENCE
